[
  {
    "id": 1930,
    "Key": "cap"
  },
  {
    "id": 1931,
    "Key": "skp"
  },
  {
    "id": 1932,
    "Key": "hlm"
  },
  {
    "id": 1933,
    "Key": "fhl"
  },
  {
    "id": 1934,
    "Key": "ghm"
  },
  {
    "id": 1935,
    "Key": "crn"
  },
  {
    "id": 1936,
    "Key": "msk"
  },
  {
    "id": 1937,
    "Key": "qui"
  },
  {
    "id": 1938,
    "Key": "lea"
  },
  {
    "id": 1939,
    "Key": "hla"
  },
  {
    "id": 1941,
    "Key": "rng"
  },
  {
    "id": 1942,
    "Key": "scl"
  },
  {
    "id": 1943,
    "Key": "chn"
  },
  {
    "id": 1944,
    "Key": "brs"
  },
  {
    "id": 1945,
    "Key": "spl"
  },
  {
    "id": 1946,
    "Key": "plt"
  },
  {
    "id": 1947,
    "Key": "fld"
  },
  {
    "id": 1948,
    "Key": "gth"
  },
  {
    "id": 1949,
    "Key": "ful"
  },
  {
    "id": 1950,
    "Key": "aar"
  },
  {
    "id": 1951,
    "Key": "ltp"
  },
  {
    "id": 1952,
    "Key": "buc"
  },
  {
    "id": 1953,
    "Key": "sml"
  },
  {
    "id": 1954,
    "Key": "lrg"
  },
  {
    "id": 1955,
    "Key": "kit"
  },
  {
    "id": 1956,
    "Key": "tow"
  },
  {
    "id": 1957,
    "Key": "gts"
  },
  {
    "id": 1969,
    "Key": "vbl"
  },
  {
    "id": 1970,
    "Key": "mbl"
  },
  {
    "id": 1973,
    "Key": "bhm"
  },
  {
    "id": 1974,
    "Key": "bsh"
  },
  {
    "id": 1975,
    "Key": "spk"
  },
  {
    "id": 1976,
    "Key": "hax"
  },
  {
    "id": 1977,
    "Key": "axe"
  },
  {
    "id": 1979,
    "Key": "mpi"
  },
  {
    "id": 1980,
    "Key": "wax"
  },
  {
    "id": 1981,
    "Key": "lax"
  },
  {
    "id": 1982,
    "Key": "bax"
  },
  {
    "id": 1983,
    "Key": "btx"
  },
  {
    "id": 1984,
    "Key": "gax"
  },
  {
    "id": 1985,
    "Key": "gix"
  },
  {
    "id": 1986,
    "Key": "wnd"
  },
  {
    "id": 1987,
    "Key": "ywn"
  },
  {
    "id": 1990,
    "Key": "clb"
  },
  {
    "id": 1991,
    "Key": "scp"
  },
  {
    "id": 1992,
    "Key": "gsc"
  },
  {
    "id": 1994,
    "Key": "spc"
  },
  {
    "id": 1995,
    "Key": "mac"
  },
  {
    "id": 1996,
    "Key": "mst"
  },
  {
    "id": 1998,
    "Key": "whm"
  },
  {
    "id": 1999,
    "Key": "mau"
  },
  {
    "id": 2000,
    "Key": "gma"
  },
  {
    "id": 2001,
    "Key": "ssd"
  },
  {
    "id": 2002,
    "Key": "scm"
  },
  {
    "id": 2003,
    "Key": "sbr"
  },
  {
    "id": 2004,
    "Key": "flc"
  },
  {
    "id": 2006,
    "Key": "bsd"
  },
  {
    "id": 2007,
    "Key": "lsd"
  },
  {
    "id": 2008,
    "Key": "wsd"
  },
  {
    "id": 2009,
    "Key": "2hs"
  },
  {
    "id": 2010,
    "Key": "clm"
  },
  {
    "id": 2011,
    "Key": "gis"
  },
  {
    "id": 2012,
    "Key": "bsw"
  },
  {
    "id": 2013,
    "Key": "flb"
  },
  {
    "id": 2014,
    "Key": "gsd"
  },
  {
    "id": 2015,
    "Key": "dgr"
  },
  {
    "id": 2016,
    "Key": "dir"
  },
  {
    "id": 2017,
    "Key": "kri"
  },
  {
    "id": 2018,
    "Key": "bld"
  },
  {
    "id": 2019,
    "Key": "tkf"
  },
  {
    "id": 2020,
    "Key": "tax"
  },
  {
    "id": 2021,
    "Key": "bkf"
  },
  {
    "id": 2022,
    "Key": "bal"
  },
  {
    "id": 2023,
    "Key": "jav"
  },
  {
    "id": 2025,
    "Key": "ssp"
  },
  {
    "id": 2026,
    "Key": "glv"
  },
  {
    "id": 2028,
    "Key": "spr"
  },
  {
    "id": 2029,
    "Key": "tri"
  },
  {
    "id": 2030,
    "Key": "brn"
  },
  {
    "id": 2031,
    "Key": "spt"
  },
  {
    "id": 2032,
    "Key": "pik"
  },
  {
    "id": 2033,
    "Key": "bar"
  },
  {
    "id": 2034,
    "Key": "vou"
  },
  {
    "id": 2036,
    "Key": "pax"
  },
  {
    "id": 2038,
    "Key": "wsc"
  },
  {
    "id": 2039,
    "Key": "sst"
  },
  {
    "id": 2040,
    "Key": "lst"
  },
  {
    "id": 2041,
    "Key": "cst"
  },
  {
    "id": 2042,
    "Key": "bst"
  },
  {
    "id": 2043,
    "Key": "wst"
  },
  {
    "id": 2044,
    "Key": "sbw"
  },
  {
    "id": 2045,
    "Key": "hbw"
  },
  {
    "id": 2047,
    "Key": "cbw"
  },
  {
    "id": 2048,
    "Key": "sbb"
  },
  {
    "id": 2049,
    "Key": "lbb"
  },
  {
    "id": 2050,
    "Key": "swb"
  },
  {
    "id": 2051,
    "Key": "lwb"
  },
  {
    "id": 2052,
    "Key": "lxb"
  },
  {
    "id": 2053,
    "Key": "mxb"
  },
  {
    "id": 2054,
    "Key": "hxb"
  },
  {
    "id": 2055,
    "Key": "rxb"
  },
  {
    "id": 2056,
    "Key": "xpk"
  },
  {
    "id": 2074,
    "Key": "xts"
  },
  {
    "id": 2075,
    "Key": "xow"
  },
  {
    "id": 2076,
    "Key": "xit"
  },
  {
    "id": 2077,
    "Key": "xrg"
  },
  {
    "id": 2078,
    "Key": "xml"
  },
  {
    "id": 2079,
    "Key": "xuc"
  },
  {
    "id": 2083,
    "Key": "xth"
  },
  {
    "id": 2084,
    "Key": "xld"
  },
  {
    "id": 2089,
    "Key": "xcl"
  },
  {
    "id": 2090,
    "Key": "xng"
  },
  {
    "id": 2091,
    "Key": "xtu"
  },
  {
    "id": 2092,
    "Key": "xla"
  },
  {
    "id": 2094,
    "Key": "xui"
  },
  {
    "id": 2099,
    "Key": "xlm"
  },
  {
    "id": 2102,
    "Key": "8rx"
  },
  {
    "id": 2104,
    "Key": "8mx"
  },
  {
    "id": 2105,
    "Key": "8lx"
  },
  {
    "id": 2107,
    "Key": "8sw"
  },
  {
    "id": 2108,
    "Key": "8l8"
  },
  {
    "id": 2109,
    "Key": "8s8"
  },
  {
    "id": 2110,
    "Key": "8cb"
  },
  {
    "id": 2111,
    "Key": "8lb"
  },
  {
    "id": 2112,
    "Key": "8hb"
  },
  {
    "id": 2113,
    "Key": "8sb"
  },
  {
    "id": 2114,
    "Key": "8ws"
  },
  {
    "id": 2115,
    "Key": "8bs"
  },
  {
    "id": 2116,
    "Key": "8cs"
  },
  {
    "id": 2117,
    "Key": "8ls"
  },
  {
    "id": 2118,
    "Key": "8ss"
  },
  {
    "id": 2119,
    "Key": "9wc"
  },
  {
    "id": 2120,
    "Key": "9h9"
  },
  {
    "id": 2121,
    "Key": "9pa"
  },
  {
    "id": 2122,
    "Key": "9s8"
  },
  {
    "id": 2123,
    "Key": "9vo"
  },
  {
    "id": 2124,
    "Key": "9b7"
  },
  {
    "id": 2125,
    "Key": "9p9"
  },
  {
    "id": 2127,
    "Key": "9br"
  },
  {
    "id": 2129,
    "Key": "9sr"
  },
  {
    "id": 2131,
    "Key": "9gl"
  },
  {
    "id": 2132,
    "Key": "9s9"
  },
  {
    "id": 2134,
    "Key": "9ja"
  },
  {
    "id": 2135,
    "Key": "9b8"
  },
  {
    "id": 2136,
    "Key": "9bk"
  },
  {
    "id": 2137,
    "Key": "9ta"
  },
  {
    "id": 2138,
    "Key": "9tk"
  },
  {
    "id": 2140,
    "Key": "9kr"
  },
  {
    "id": 2141,
    "Key": "9di"
  },
  {
    "id": 2142,
    "Key": "9dg"
  },
  {
    "id": 2143,
    "Key": "9gd"
  },
  {
    "id": 2145,
    "Key": "9gs"
  },
  {
    "id": 2146,
    "Key": "9cm"
  },
  {
    "id": 2147,
    "Key": "92h"
  },
  {
    "id": 2148,
    "Key": "9wd"
  },
  {
    "id": 2149,
    "Key": "9ls"
  },
  {
    "id": 2151,
    "Key": "9cr"
  },
  {
    "id": 2153,
    "Key": "9sb"
  },
  {
    "id": 2155,
    "Key": "9ss"
  },
  {
    "id": 2156,
    "Key": "9gm"
  },
  {
    "id": 2157,
    "Key": "9m9"
  },
  {
    "id": 2158,
    "Key": "9wh"
  },
  {
    "id": 2159,
    "Key": "9fl"
  },
  {
    "id": 2161,
    "Key": "9ma"
  },
  {
    "id": 2162,
    "Key": "9sp"
  },
  {
    "id": 2164,
    "Key": "9qs"
  },
  {
    "id": 2165,
    "Key": "9sc"
  },
  {
    "id": 2166,
    "Key": "9cl"
  },
  {
    "id": 2171,
    "Key": "9gi"
  },
  {
    "id": 2172,
    "Key": "9ga"
  },
  {
    "id": 2173,
    "Key": "9bt"
  },
  {
    "id": 2174,
    "Key": "9ba"
  },
  {
    "id": 2175,
    "Key": "9la"
  },
  {
    "id": 2176,
    "Key": "9wa"
  },
  {
    "id": 2177,
    "Key": "9mp"
  },
  {
    "id": 2178,
    "Key": "92a"
  },
  {
    "id": 2179,
    "Key": "9ax"
  },
  {
    "id": 2180,
    "Key": "9ha"
  },
  {
    "id": 2181,
    "Key": "9b9"
  },
  {
    "id": 2182,
    "Key": "gpl"
  },
  {
    "id": 2183,
    "Key": "opl"
  },
  {
    "id": 2184,
    "Key": "gpm"
  },
  {
    "id": 2185,
    "Key": "opm"
  },
  {
    "id": 2186,
    "Key": "gps"
  },
  {
    "id": 2187,
    "Key": "ops"
  },
  {
    "id": 2207,
    "Key": "vps"
  },
  {
    "id": 2208,
    "Key": "yps"
  },
  {
    "id": 2211,
    "Key": "wms"
  },
  {
    "id": 2218,
    "Key": "aqv"
  },
  {
    "id": 2220,
    "Key": "cqv"
  },
  {
    "id": 2222,
    "Key": "key"
  },
  {
    "id": 2266,
    "Key": "hp1"
  },
  {
    "id": 2267,
    "Key": "hp2"
  },
  {
    "id": 2268,
    "Key": "hp3"
  },
  {
    "id": 2269,
    "Key": "hp4"
  },
  {
    "id": 2271,
    "Key": "mp1"
  },
  {
    "id": 2272,
    "Key": "mp2"
  },
  {
    "id": 2273,
    "Key": "mp3"
  },
  {
    "id": 2274,
    "Key": "mp4"
  },
  {
    "id": 11028,
    "Key": "9bl"
  },
  {
    "id": 20292,
    "Key": "am1"
  },
  {
    "id": 20293,
    "Key": "am2"
  },
  {
    "id": 20294,
    "Key": "am3"
  },
  {
    "id": 20295,
    "Key": "am4"
  },
  {
    "id": 20296,
    "Key": "am5"
  },
  {
    "id": 20302,
    "Key": "am6"
  },
  {
    "id": 20303,
    "Key": "am7"
  },
  {
    "id": 20304,
    "Key": "am8"
  },
  {
    "id": 20305,
    "Key": "am9"
  },
  {
    "id": 20327,
    "Key": "pa1"
  },
  {
    "id": 20328,
    "Key": "pa2"
  },
  {
    "id": 20329,
    "Key": "pa3"
  },
  {
    "id": 20330,
    "Key": "pa4"
  },
  {
    "id": 20331,
    "Key": "pa5"
  }
]