[
  {
    "id": 20510,
    "Key": "Runeword4",
    "zhCN": "狂热光环，纯招及武学刺常用"
  },
  {
    "id": 20515,
    "Key": "Runeword9",
    "zhCN": "不如tp甲有用，土豪玩物"
  },
  {
    "id": 20517,
    "Key": "Runeword11",
    "zhCN": "冷兵器之王，打钱蛮子米山用"
  },
  {
    "id": 20522,
    "Key": "Runeword16",
    "zhCN": "武艺超群"
  },
  {
    "id": 20523,
    "Key": "Runeword17",
    "zhCN": "电法常用，对高电抗怪物效果明显"
  },
  {
    "id": 20526,
    "Key": "Runeword20",
    "zhCN": "与年纪哥俩好"
  },
  {
    "id": 20532,
    "Key": "Runeword26",
    "zhCN": "风德常用"
  },
  {
    "id": 20535,
    "Key": "Runeword29",
    "zhCN": "双梦法师和圣骑必备，目前bug已取消"
  },
  {
    "id": 20536,
    "Key": "Runeword30",
    "zhCN": "Kboss常用，穷人米山可穿它"
  },
  {
    "id": 20537,
    "Key": "Runeword31",
    "zhCN": "俗称赌博弓，赌博常用"
  },
  {
    "id": 20539,
    "Key": "Runeword33",
    "zhCN": "脱贫甲，与无限一起成为土豪标志（新人版）"
  },
  {
    "id": 20543,
    "Key": "Runeword37",
    "zhCN": "PK或者K6盾击最常用，PVC不如饰金盾"
  },
  {
    "id": 20544,
    "Key": "Runeword38",
    "zhCN": "弓马进阶必备，可手抓也可给京子"
  },
  {
    "id": 20547,
    "Key": "Runeword41",
    "zhCN": "物理系第一甲，别忘了它还混武器界"
  },
  {
    "id": 20553,
    "Key": "Runeword47",
    "zhCN": "单手武器之王，别以为它的ias不重要，中衰老试试？"
  },
  {
    "id": 20555,
    "Key": "Runeword49",
    "zhCN": "跑步弓，多用于副手"
  },
  {
    "id": 20557,
    "Key": "Runeword51",
    "zhCN": "教主神器，法系万金油"
  },
  {
    "id": 20565,
    "Key": "Runeword59",
    "zhCN": "元素弓土豪玩物"
  },
  {
    "id": 20566,
    "Key": "Runeword60",
    "zhCN": "其实我一直很想教超级劳模做魔（娱乐版）"
  },
  {
    "id": 20568,
    "Key": "Runeword62",
    "zhCN": "性价比最高的RW之二，续航神器，6cs输出也是杠杠的"
  },
  {
    "id": 20572,
    "Key": "Runeword66",
    "zhCN": "不知道黑毛看了它怕不怕"
  },
  {
    "id": 20575,
    "Key": "Runeword69",
    "zhCN": "有钱就是任性"
  },
  {
    "id": 20577,
    "Key": "Runeword71",
    "zhCN": "城管剑，通常开荒放副手"
  },
  {
    "id": 20596,
    "Key": "Runeword91",
    "zhCN": "平民武器之王"
  },
  {
    "id": 20597,
    "Key": "Runeword92",
    "zhCN": "综合性不错的武器，纯招米山或狼德可过渡"
  },
  {
    "id": 20600,
    "Key": "Runeword95",
    "zhCN": "狂战士能拿来破物免"
  },
  {
    "id": 20608,
    "Key": "Runeword103",
    "zhCN": "续航神器，火法或者武学刺要带它"
  },
  {
    "id": 20614,
    "Key": "Runeword109",
    "zhCN": "土豪弓马米山拿，土豪纯招做铁魔"
  },
  {
    "id": 20626,
    "Key": "Runeword121",
    "zhCN": "烟花棒"
  },
  {
    "id": 20635,
    "Key": "Runeword130",
    "zhCN": "性价比最高的RW之一，很多法系终配，35fcr最关键"
  },
  {
    "id": 20636,
    "Key": "Runeword131",
    "zhCN": "初期MF很实用"
  },
  {
    "id": 20642,
    "Key": "Runeword137",
    "zhCN": "尴尬的装甲，有钱人可以做来玩玩，用途不大"
  }
]